{
    "resourceType": "CodeSystem",
    "id": "UKCore-SDSJobRoleName",
    "url": "https://fhir.nhs.uk/CodeSystem/NHSDigital-SDS-JobRoleCode",
    "version": "2.0.0",
    "name": "NHSDigitalSDSJobRoleCode",
    "title": "NHSDigital SDS Job Role Code",
    "status": "active",
    "date": "2022-06-23",
    "publisher": "NHS Digital",
    "contact":  [
        {
            "name": "NHS Digital",
            "telecom":  [
                {
                    "system": "email",
                    "value": "interoperabilityteam@nhs.net",
                    "use": "work",
                    "rank": 2
                }
            ]
        }
    ],
    "description": "A CodeSystem that identifies the job role associated with the person on the smart card. This consists of a set of Role Based Access Control (RBAC) codes. This code list is externally maintained.",
    "copyright": "Copyright &#169; 2022 NHS Digital.",
    "caseSensitive": true,
    "content": "not-present"
}